.codebeatignore
.gitignore
Dockerfile
LICENSE
MANIFEST.in
Makefile
README.md
UPGRADE
me.opml
pyproject.toml
sanity.py
setup.py
temboz
test.py
unit_test.py
bugfeed/DigitalOutbackPhoto_News.xml
bugfeed/PetaPixel
bugfeed/QuantifiedSelf
bugfeed/barnett
bugfeed/boingboing
bugfeed/calmatters
bugfeed/case1
bugfeed/case2
bugfeed/case3
bugfeed/cooltools
bugfeed/greenwald
bugfeed/nettuts
bugfeed/russellbeattieweblog
bugfeed/tokyo
bugfeed/tychay
bugfeed/typographica
etc/db_0.5.sh
etc/norm_url.py
etc/resolveguid.py
temboz.egg-info/PKG-INFO
temboz.egg-info/SOURCES.txt
temboz.egg-info/dependency_links.txt
temboz.egg-info/requires.txt
temboz.egg-info/top_level.txt
tembozapp/__init__.py
tembozapp/aia.py
tembozapp/autodiscovery.py
tembozapp/bootstrap.py
tembozapp/dbop.py
tembozapp/ddl.sql
tembozapp/degunk.py
tembozapp/feedfix.py
tembozapp/filters.py
tembozapp/fts5.py
tembozapp/normalize.py
tembozapp/opml.py
tembozapp/param.py
tembozapp/porter2.py
tembozapp/server.py
tembozapp/sop.py
tembozapp/transform.py
tembozapp/update.py
tembozapp/urldedup.py
tembozapp/util.py
tembozapp/static/add.js
tembozapp/static/dygraph-combined.js
tembozapp/static/iphone.css
tembozapp/static/item.mst
tembozapp/static/mustache.js
tembozapp/static/specific.js
tembozapp/static/temboz.css
tembozapp/static/temboz.js
tembozapp/static/trumbowyg.min.css
tembozapp/static/trumbowyg.min.js
tembozapp/static/ui/icons.svg
tembozapp/static/ui/trumbowyg.css
tembozapp/static/ui/sass/trumbowyg.scss
tembozapp/templates/_share.atom
tembozapp/templates/add.html
tembozapp/templates/edit.html
tembozapp/templates/edit.html~
tembozapp/templates/feed.html
tembozapp/templates/feed_debug.html
tembozapp/templates/feeds.html
tembozapp/templates/login.html
tembozapp/templates/menubar.html
tembozapp/templates/offline.html
tembozapp/templates/opml.opml
tembozapp/templates/rules.html
tembozapp/templates/rules_common.html
tembozapp/templates/settings.html
tembozapp/templates/threads.html
tembozapp/templates/view.html
test/category.opml
test/directory.opml
test/placesLived.opml
test/simpleScript.opml
test/states.opml
test/subscriptionList.opml