Metadata-Version: 2.1
Name: temboz
Version: 4.12
Summary: The Temboz RSS/Atom feed reader and aggregator.
Home-page: https://github.com/fazalmajid/temboz
Author: Fazal Majid
Author-email: python@sentfrom.com
Classifier: License :: OSI Approved :: BSD License
Classifier: Programming Language :: Python
Classifier: Programming Language :: Python :: 3.8
Classifier: Programming Language :: Python :: 3.9
Classifier: Programming Language :: Python :: 3.10
Classifier: Programming Language :: Python :: 3.11
Classifier: Programming Language :: Python :: 3.12
License-File: LICENSE
Requires-Dist: flask
Requires-Dist: requests
Requires-Dist: html5lib>=1.1
Requires-Dist: passlib
Requires-Dist: argon2_cffi
Requires-Dist: ctranslitcodec
Requires-Dist: sgmllib3k
Requires-Dist: feedparser>=6.0.2
Requires-Dist: werkzeug>=1.0.1
Requires-Dist: bleach>=5.0.1
Requires-Dist: yappi
